genurl/__init__.py
genurl/genurl.py
genurl-0.2.2.dist-info/entry_points.txt
genurl-0.2.2.dist-info/WHEEL
genurl-0.2.2.dist-info/METADATA
genurl-0.2.2.dist-info/RECORD
